remotesystemlogger/__init__.py
remotesystemlogger/remotesystemlogger.py
remotesystemlogger-1.0.1.dist-info/LICENSE.txt
remotesystemlogger-1.0.1.dist-info/METADATA
remotesystemlogger-1.0.1.dist-info/WHEEL
remotesystemlogger-1.0.1.dist-info/top_level.txt
remotesystemlogger-1.0.1.dist-info/RECORD
