Metadata-Version: 2.1
Name: remotesystemlogger
Version: 1.0.1
Summary: Please do not use this library
Author: Andre Buck
Classifier: Programming Language :: Python :: 3
Classifier: License :: OSI Approved :: MIT License
Classifier: Operating System :: OS Independent
Requires-Python: >=3.6
License-File: LICENSE.txt
